Structure/Atom.py
Structure/CIFIO.py
Structure/QEIO.py
Structure/__init__.py
Structure/controls.py
Structure/tags
probingmc-2.9.0.post3.dist-info/licenses/LICENSE
probingmc-2.9.0.post3.dist-info/METADATA
probingmc-2.9.0.post3.dist-info/WHEEL
probingmc-2.9.0.post3.dist-info/top_level.txt
probingmc-2.9.0.post3.dist-info/RECORD
