Metadata-Version: 2.4
Name: ProbingMC
Version: 2.9.0.post3
Summary: Core tools for crystal structures, CIF/XYZ I/O, and Quantum ESPRESSO input/output
Author: Andrey Tokarev
License: MIT License
Project-URL: Homepage, https://github.com/Andrey-Tokarev/probingmc
Project-URL: Issues, https://github.com/Andrey-Tokarev/probingmc/issues
Classifier: Programming Language :: Python :: 3
Classifier: Programming Language :: Python :: 3.10
Classifier: License :: OSI Approved :: MIT License
Classifier: Intended Audience :: Science/Research
Classifier: Topic :: Scientific/Engineering :: Chemistry
Classifier: Topic :: Scientific/Engineering :: Physics
Classifier: Operating System :: OS Independent
Requires-Python: >=3.10
License-File: LICENSE
Requires-Dist: numpy
Requires-Dist: ase
Dynamic: license-file
